{"nodes": [{"id": "cadsmith", "label": "CADSmith", "file_type": "concept", "source_file": "docs/project/codebase-map.md", "source_location": null, "source_url": null, "captured_at": null, "author": null, "contributor": null}, {"id": "temporal", "label": "Temporal", "file_type": "concept", "source_file": "docs/project/codebase-map.md", "source_location": null, "source_url": null, "captured_at": null, "author": null, "contributor": null}, {"id": "cadquery", "label": "CadQuery", "file_type": "concept", "source_file": "docs/project/codebase-map.md", "source_location": null, "source_url": null, "captured_at": null, "author": null, "contributor": null}], "edges": [{"source": "main_py", "target": "harness_api_static_index_html", "relation": "references", "confidence": "INFERRED", "confidence_score": 0.8, "source_file": "docs/project/codebase-map.md", "source_location": null, "weight": 1.0}, {"source": "main_py", "target": "temporal", "relation": "calls", "confidence": "EXTRACTED", "confidence_score": 1.0, "source_file": "docs/project/codebase-map.md", "source_location": null, "weight": 1.0}, {"source": "main_py", "target": "cadquery", "relation": "calls", "confidence": "EXTRACTED", "confidence_score": 1.0, "source_file": "docs/project/codebase-map.md", "source_location": null, "weight": 1.0}], "hyperedges": []}